Metadata-Version: 2.1
Name: mksgrd-sample-package
Version: 0.3.1
Summary: An example Python package
Home-page: https://github.com/mksgrd
Author: Maxim Gordienko
Author-email: maksgord-152@yandex.ru
License: MIT
Platform: UNKNOWN
